flowsplit/__init__.py
flowsplit/splitter.py
flowsplit-1.0.dist-info/LICENSE
flowsplit-1.0.dist-info/METADATA
flowsplit-1.0.dist-info/WHEEL
flowsplit-1.0.dist-info/entry_points.txt
flowsplit-1.0.dist-info/top_level.txt
flowsplit-1.0.dist-info/RECORD
