Metadata-Version: 2.1
Name: flowsplit
Version: 1.0
Summary: 将pcap文件按照session或者flow进行分隔
Home-page: https://github.com/ZGC-BUPT-aimafan/flowsplit.git
Author: ZGC-BUPT-aimafan
Author-email: chongrufan@nuaa.edu.cn
Classifier: Programming Language :: Python :: 3
Classifier: License :: OSI Approved :: MIT License
Requires-Python: >=3.8
License-File: LICENSE
Requires-Dist: dpkt ==1.9.8
Requires-Dist: scapy ==2.6.0
